AUTHORS
CHANGELOG.txt
DESCRIPTION
LICENSE
MANIFEST.in
setup.py
django_roadmap.egg-info/PKG-INFO
django_roadmap.egg-info/SOURCES.txt
django_roadmap.egg-info/dependency_links.txt
django_roadmap.egg-info/top_level.txt
roadmap/__init__.py
roadmap/admin.py
roadmap/cms_app.py
roadmap/models.py
roadmap/simple_translate.py
roadmap/urls.py
roadmap/views.py
roadmap/fixtures/bootstrap.json
roadmap/migrations/0001_initial.py
roadmap/migrations/0002_auto__add_eventtranslation__add_event.py
roadmap/migrations/0003_rename_translation_model.py
roadmap/migrations/0004_auto__add_eventtranslation__add_unique_eventtranslation_language_code_.py
roadmap/migrations/0005_move_from_simpletranslation_to_hvad.py
roadmap/migrations/__init__.py
roadmap/templates/roadmap/milestone_list.html
roadmap/templatetags/__init__.py
roadmap/templatetags/roadmap_tags.py
roadmap/tests/__init__.py
roadmap/tests/factories.py
roadmap/tests/models_tests.py
roadmap/tests/roadmap_tags_tests.py
roadmap/tests/runtests.py
roadmap/tests/south_settings.py
roadmap/tests/test_settings.py
roadmap/tests/integration_tests/__init__.py
roadmap/tests/integration_tests/views_tests.py
roadmap/tests/test_app/__init__.py
roadmap/tests/test_app/models.py
roadmap/tests/test_app/urls.py
roadmap/tests/test_app/templates/base.html
roadmap/tests/test_app/templates/standard.html