Metadata-Version: 1.0
Name: django-roadmap
Version: 0.2
Summary: A simple app to display a project roadmap with milestones and events.
